ultrawhisper/__init__.py
ultrawhisper/app.py
ultrawhisper/cli.py
ultrawhisper/context.py
ultrawhisper/logging_config.py
ultrawhisper/text_utils.py
ultrawhisper/audio/recorder.py
ultrawhisper/config/config.py
ultrawhisper/config/models.py
ultrawhisper/llm/agent_service.py
ultrawhisper/llm/llm_service.py
ultrawhisper/llm/text_corrector.py
ultrawhisper/modes/conversation_history.py
ultrawhisper/modes/mode.py
ultrawhisper/modes/mode_logger.py
ultrawhisper/modes/mode_manager.py
ultrawhisper/transcription/whisper_transcriber.py
ultrawhisper/tts/system_tts.py
ultrawhisper/tts/tts_service.py
ultrawhisper/ui/ascii_art.py
ultrawhisper/ui/hotkey_manager.py
ultrawhisper/ui/notifications.py
ultrawhisper/ui/settings_screen.py
ultrawhisper/ui/simple_tui.py
ultrawhisper/ui/text_outputter.py
ultrawhisper-1.0.1.dist-info/METADATA
ultrawhisper-1.0.1.dist-info/WHEEL
ultrawhisper-1.0.1.dist-info/entry_points.txt
ultrawhisper-1.0.1.dist-info/licenses/LICENSE
ultrawhisper-1.0.1.dist-info/RECORD
