Metadata-Version: 2.4
Name: ultrawhisper
Version: 1.0.1
Summary: Voice transcription with global hotkeys and LLM correction
Project-URL: Homepage, https://github.com/casonclagg/ultrawhisper
Project-URL: Repository, https://github.com/casonclagg/ultrawhisper.git
Project-URL: Issues, https://github.com/casonclagg/ultrawhisper/issues
Author-email: Cason Clagg <cason@cason.cc>
License: MIT
License-File: LICENSE
Keywords: hotkey,llm,speech-to-text,transcription,voice,whisper
Classifier: Development Status :: 4 - Beta
Classifier: Environment :: X11 Applications
Classifier: Intended Audience :: End Users/Desktop
Classifier: License :: OSI Approved :: MIT License
Classifier: Operating System :: POSIX :: Linux
Classifier: Programming Language :: Python :: 3
Classifier: Programming Language :: Python :: 3.8
Classifier: Programming Language :: Python :: 3.9
Classifier: Programming Language :: Python :: 3.10
Classifier: Programming Language :: Python :: 3.11
Classifier: Programming Language :: Python :: 3.12
Classifier: Topic :: Multimedia :: Sound/Audio :: Speech
Classifier: Topic :: Text Processing :: Linguistic
Classifier: Topic :: Utilities
Requires-Python: >=3.10
Requires-Dist: anthropic>=0.20.0
Requires-Dist: faster-whisper>=0.10.0
Requires-Dist: loguru>=0.7.0
Requires-Dist: numpy>=1.20.0
Requires-Dist: openai-agents
Requires-Dist: openai>=1.0.0
Requires-Dist: platformdirs>=3.0.0
Requires-Dist: prompt-toolkit>=3.0.0
Requires-Dist: pynput>=1.7.0
Requires-Dist: pyperclip>=1.8.0
Requires-Dist: pyyaml>=6.0
Requires-Dist: requests>=2.25.0
Requires-Dist: scipy>=1.7.0
Requires-Dist: sounddevice>=0.4.0
Requires-Dist: unidecode>=1.3.0
Requires-Dist: wavio>=0.0.4
Provides-Extra: dev
Requires-Dist: black>=22.0; extra == 'dev'
Requires-Dist: flake8>=4.0; extra == 'dev'
Requires-Dist: mypy>=1.0; extra == 'dev'
Requires-Dist: pytest>=7.0; extra == 'dev'
